LICENSE
MANIFEST.in
README.md
VERSION
setup.cfg
setup.py
graphql_service_framework/__init__.py
graphql_service_framework/query.graphql
graphql_service_framework/schema.py
graphql_service_framework/schema_tracker.py
graphql_service_framework/service.py
graphql_service_framework/service_manager.py
graphql_service_framework/service_manager_middleware.py
graphql_service_framework/utils.py
graphql_service_framework.egg-info/PKG-INFO
graphql_service_framework.egg-info/SOURCES.txt
graphql_service_framework.egg-info/dependency_links.txt
graphql_service_framework.egg-info/requires.txt
graphql_service_framework.egg-info/top_level.txt
tests/__init__.py
tests/conftest.py
tests/test_dispatcher.py
tests/test_schema.py
tests/test_service.py
tests/test_service_manager.py
tests/utils.py